rm_lines_sys/__init__.py
rm_lines_sys/librm_lines.so
rm_lines_sys-1.3.dist-info/METADATA
rm_lines_sys-1.3.dist-info/WHEEL
rm_lines_sys-1.3.dist-info/RECORD
