Metadata-Version: 2.4
Name: rm_lines_sys
Version: 1.3
Summary: This project holds the dynamic library and bindings for python.
Author: RedTTG
Author-email: red@redttg.com
Requires-Python: >=3.9
Classifier: Programming Language :: Python :: 3
Classifier: Programming Language :: Python :: 3.9
Classifier: Programming Language :: Python :: 3.10
Classifier: Programming Language :: Python :: 3.11
Classifier: Programming Language :: Python :: 3.12
Classifier: Programming Language :: Python :: 3.13
Classifier: Programming Language :: Python :: 3.14
